pgm/__init__.py
pgm/calculator.py
pgm/data.py
pgm/interpolate.py
pgm/settings.py
pgm/thermo.py
pgm/v2p.py
pgm/version.py
pgm/cli/__init__.py
pgm/cli/banner.py
pgm/cli/cli.py
pgm/cli/main.py
pgm/cli/plot.py
pgm/plot/__init__.py
pgm/plot/plotter.py
pgm/reader/__init__.py
pgm/reader/read_input.py
pgm/util/__init__.py
pgm/util/fitting.py
pgm/util/grid_interpolation.py
pgm/util/tools.py
pgm/util/unit_conversion.py
phonon_gas_model-1.0.0a0.dist-info/LICENSE.txt
phonon_gas_model-1.0.0a0.dist-info/METADATA
phonon_gas_model-1.0.0a0.dist-info/WHEEL
phonon_gas_model-1.0.0a0.dist-info/entry_points.txt
phonon_gas_model-1.0.0a0.dist-info/top_level.txt
phonon_gas_model-1.0.0a0.dist-info/RECORD
