Metadata-Version: 2.1
Name: phonon-gas-model
Version: 1.0.0a0
Summary: Free energy calculation using phonon gas model
Home-page: https://github.com/MineralsCloud/pgm/
Author: Hongjin Wang, Jingyi Zhuang
Author-email: hw2626@columbia.edu, jz2907@columbia.edu
License-File: LICENSE.txt
Requires-Dist: click
Requires-Dist: cycler
Requires-Dist: kiwisolver
Requires-Dist: lazy-property
Requires-Dist: llvmlite
Requires-Dist: matplotlib
Requires-Dist: numba
Requires-Dist: numpy
Requires-Dist: pandas
Requires-Dist: pyparsing
Requires-Dist: python-dateutil
Requires-Dist: pytz
Requires-Dist: PyYAML
Requires-Dist: scientific-string
Requires-Dist: scipy
Requires-Dist: seaborn
Requires-Dist: six
Requires-Dist: text-stream
